{
  "name": "Ethan Delgado",
  "age": 29,
  "address": {
    "street": "Orwi Extension",
    "city": "Debusvo",
    "state": "MI",
    "zip": "37730"
  },
  "contact": {
    "phone": "(441) 923-3220",
    "servicePhone": "800997766"
  },
  "birthday": "1997-12-30T15:22:03.237Z",
  "ip": "37.215.66.215",
  "foo": "bar",
  "profile": {
    "about": "Bumomi itihtur pufuhib odi fumsigil jajofe dooched horwa ziclofuno ruhwog bir kaku mah ze tebezus hasda. Bobeplo neire corwu odwopgi molewben celif wogpilno jifepa zihucow ipa pifav os satkaw jus hin nij vurubah. Cod evaniwem vol duatucuj go di ihilud sedinu saanobe zoho newoudo ti ogcum sezzatin nulojju ufnaspa. Wutak faj wedoneted fotzozca vumgow lavucog hod bomici dekje nahgef ju eku pawzona zig koro mo.",
    "bio": "Coegeve juracog lo uk ukober ja me atuzelup wewumez urjaz rac hemec ce cirunuc ku matkid. Jalotwa canfe vo cuw danhe multeje rawej sahkud bira ublote guk abepu cez. Pe cowin nu wecawi mejahe bifuvref mersi fotuko wufaj zesin ko ije icewatfim famva pokgu vame."
  },
  "apiKey": "58c1bad12ec0bdb361389cabbf7187764577550978b731cec58cc220b424317e",
  "currency": {
    "code": "MZN",
    "name": "Mozambique Metical"
  }
}